{
  "totalRoutes": 1519,
  "checkedFiles": 3587,
  "brokenLinks": 44,
  "links": [
    {
      "file": "app/calculator/revenue-share/page.tsx",
      "href": "/docs/revenue-sharing-policy.md"
    },
    {
      "file": "app/cm/learners/[id]/page.tsx",
      "href": "/cm/learners"
    },
    {
      "file": "app/demos/page.tsx",
      "href": "/success-stories"
    },
    {
      "file": "app/ferpa/compliance/page.tsx",
      "href": "/ferpa/training"
    },
    {
      "file": "app/fundingimpact/page.tsx",
      "href": "/success-stories"
    },
    {
      "file": "app/layout.tsx",
      "href": "/favicon.ico"
    },
    {
      "file": "app/layout.tsx",
      "href": "/favicon.png"
    },
    {
      "file": "app/layout.tsx",
      "href": "/apple-touch-icon.png"
    },
    {
      "file": "app/legal/governance/compliance/page.tsx",
      "href": "/docs/Compliance_and_Disclosure_Framework.pdf"
    },
    {
      "file": "app/legal/governance/lms-standards/page.tsx",
      "href": "/docs/LMS_Governance_and_Course_Standards.pdf"
    },
    {
      "file": "app/legal/governance/onboarding-ux/page.tsx",
      "href": "/docs/Onboarding_User_Experience_Standards.pdf"
    },
    {
      "file": "app/legal/governance/platform-overview/page.tsx",
      "href": "/docs/Platform_Overview_and_Governance.pdf"
    },
    {
      "file": "app/legal/governance/security/page.tsx",
      "href": "/docs/Security_and_Data_Protection_Statement.pdf"
    },
    {
      "file": "app/legal/governance/store-payments/page.tsx",
      "href": "/docs/Store_Payments_Licensing_Framework.pdf"
    },
    {
      "file": "app/legal/governance/tax-operations/page.tsx",
      "href": "/docs/Tax_Preparation_Refund_Advance_Operations.pdf"
    },
    {
      "file": "app/lms/(app)/collaborate/page.tsx",
      "href": "/lms/collaborate/meetings"
    },
    {
      "file": "app/lms/(app)/social/page.tsx",
      "href": "/lms/social/connections"
    },
    {
      "file": "app/lms/(app)/social/page.tsx",
      "href": "/lms/social/groups"
    },
    {
      "file": "app/lms/(app)/social/page.tsx",
      "href": "/lms/social/trending"
    },
    {
      "file": "app/lms/(app)/social/page.tsx",
      "href": "/lms/social/connections"
    },
    {
      "file": "app/lms/(app)/social/page.tsx",
      "href": "/lms/social/groups"
    },
    {
      "file": "app/lms/(app)/social/page.tsx",
      "href": "/lms/social/connections"
    },
    {
      "file": "app/lms/(app)/social/page.tsx",
      "href": "/lms/social/groups/healthcare"
    },
    {
      "file": "app/lms/(app)/social/page.tsx",
      "href": "/lms/social/groups/trades"
    },
    {
      "file": "app/lms/(app)/social/page.tsx",
      "href": "/lms/social/groups/career"
    },
    {
      "file": "app/lms/(app)/social/page.tsx",
      "href": "/lms/social/groups"
    },
    {
      "file": "app/mentorship/page.tsx",
      "href": "/mentorship/apply"
    },
    {
      "file": "app/mentorship/page.tsx",
      "href": "/mentorship/become-mentor"
    },
    {
      "file": "app/onboarding/employer/page.tsx",
      "href": "/onboarding/employer/hiring-needs"
    },
    {
      "file": "app/program-holder/courses/create/page.tsx",
      "href": "/program-holder/courses"
    },
    {
      "file": "app/program-holder/courses/create/page.tsx",
      "href": "/program-holder/courses"
    },
    {
      "file": "app/staff-portal/attendance/page.tsx",
      "href": "/staff-portal/attendance/take"
    },
    {
      "file": "app/staff-portal/attendance/page.tsx",
      "href": "/staff-portal/attendance/export"
    },
    {
      "file": "app/staff-portal/courses/page.tsx",
      "href": "/staff-portal/courses/create"
    },
    {
      "file": "app/suboffice-onboarding/page.tsx",
      "href": "/suboffice-onboarding/payout-policy.pdf"
    },
    {
      "file": "components/community/ActivityFeed.tsx",
      "href": "/community/activity"
    },
    {
      "file": "components/compliance/FERPATrainingForm.tsx",
      "href": "/docs/compliance/ferpa/FERPA_Policy_Manual.md"
    },
    {
      "file": "components/compliance/FERPATrainingForm.tsx",
      "href": "/docs/compliance/ferpa/FERPA_Training_Course.md"
    },
    {
      "file": "components/compliance/FERPATrainingForm.tsx",
      "href": "/docs/compliance/lms/LMS_Policies_Manual.md"
    },
    {
      "file": "components/licensing/TrialBanner.tsx",
      "href": "/support/documentation"
    },
    {
      "file": "components/marketing/SuccessStoryCards.tsx",
      "href": "/success-stories"
    },
    {
      "file": "components/shop/ShopDocumentUpload.tsx",
      "href": "/docs/templates/EFH_Shop_MOU_Indiana.pdf"
    },
    {
      "file": "components/shop/ShopDocumentUpload.tsx",
      "href": "/docs/templates/EFH_NDA_IP_Acknowledgment.pdf"
    },
    {
      "file": "components/shop/ShopDocumentUpload.tsx",
      "href": "/docs/templates/EFH_Non_Compete_Indiana.pdf"
    }
  ]
}